LongPathShutil/LongPathShutil.py
LongPathShutil/__init__.py
longpathshutil-0.5.dist-info/licenses/LICENSE
longpathshutil-0.5.dist-info/METADATA
longpathshutil-0.5.dist-info/WHEEL
longpathshutil-0.5.dist-info/top_level.txt
longpathshutil-0.5.dist-info/RECORD
