Metadata-Version: 2.4
Name: LongPathShutil
Version: 0.5
Summary: Drop-in replacement for shutil with long path support for Windows
Author: Simon Mueller
Project-URL: Homepage, https://github.com/simonmb/LongPathShutil
Classifier: Programming Language :: Python :: 3
Classifier: License :: OSI Approved :: MIT License
Classifier: Operating System :: OS Independent
Requires-Python: >=3.6
License-File: LICENSE
Dynamic: license-file
